py_anycase-0.1.0.dist-info/METADATA
py_anycase-0.1.0.dist-info/WHEEL
py_anycase-0.1.0.dist-info/licenses/LICENSE-APACHE
py_anycase-0.1.0.dist-info/licenses/LICENSE-MIT
anycase/__init__.pyi
anycase/py.typed
anycase/__init__.py
anycase/anycase.cpython-37m-arm-linux-gnueabihf.so
py_anycase-0.1.0.dist-info/RECORD
