Metadata-Version: 2.4
Name: py-anycase
Version: 0.1.0
Classifier: Development Status :: 3 - Alpha
Classifier: Intended Audience :: Developers
Classifier: License :: OSI Approved :: MIT License
Classifier: License :: OSI Approved :: Apache Software License
Classifier: Natural Language :: English
Classifier: Operating System :: OS Independent
Classifier: Programming Language :: Rust
Classifier: Programming Language :: Python
Classifier: Programming Language :: Python :: 3.7
Classifier: Programming Language :: Python :: 3.8
Classifier: Programming Language :: Python :: 3.9
Classifier: Programming Language :: Python :: 3.10
Classifier: Programming Language :: Python :: 3.11
Classifier: Programming Language :: Python :: 3.12
Classifier: Programming Language :: Python :: 3.13
License-File: LICENSE-APACHE
License-File: LICENSE-MIT
Summary: A case conversion library with Unicode support
Keywords: convert,case,snake,camel,pascal
Author-email: Ross MacArthur <ross@macarthur.io>
License: MIT OR Apache-2.0
Requires-Python: >=3.7
Project-URL: Homepage, https://github.com/rossmacarthur/anycase
Project-URL: Repository, https://github.com/rossmacarthur/anycase
